{
    "Exposes": [
        {
            "Index": 0,
            "Name": "VOL_SYS_V",
            "ScaleFactor": 0.1124,
            "MaxValue": 5,
            "MinValue": 0,
            "Thresholds": [
                {
                    "Direction": "greater than",
                    "Name": "upper critical",
                    "Severity": 1,
                    "Value": 12.6
                },
                {
                    "Direction": "less than",
                    "Name": "lower critical",
                    "Severity": 1,
                    "Value": 11.4
                }
            ],
            "Type": "ADC"
        },
        {
            "Index": 1,
            "Name": "VOL_SYS_3_3V",
            "ScaleFactor": 0.410678,
            "MaxValue": 7,
            "MinValue": 0,
            "Thresholds": [
                {
                    "Direction": "greater than",
                    "Name": "upper critical",
                    "Severity": 1,
                    "Value": 3.47
                },
                {
                    "Direction": "less than",
                    "Name": "lower critical",
                    "Severity": 1,
                    "Value": 3.14
                }
            ],
            "Type": "ADC"
        },
        {
            "Index": 2,
            "Name": "VOL_PCH_VNN",
            "ScaleFactor": 1,
            "MaxValue": 7,
            "MinValue": 0,
            "Thresholds": [
                {
                    "Direction": "greater than",
                    "Name": "upper critical",
                    "Severity": 1,
                    "Value": 1.05
                },
                {
                    "Direction": "less than",
                    "Name": "lower critical",
                    "Severity": 1,
                    "Value": 0.95
                }
            ],
            "Type": "ADC"
        },
        {
            "Index": 3,
            "Name": "VOL_PCH_1_05V",
            "ScaleFactor": 1,
            "MaxValue": 2,
            "MinValue": 0,
            "Thresholds": [
                {
                    "Direction": "greater than",
                    "Name": "upper critical",
                    "Severity": 1,
                    "Value": 1.1
                },
                {
                    "Direction": "less than",
                    "Name": "lower critical",
                    "Severity": 1,
                    "Value": 0.99
                }
            ],
            "Type": "ADC"
        },
        {
            "Index": 4,
            "Name": "VOL_3_3V_AUX",
            "ScaleFactor": 0.410678,
            "MaxValue": 5,
            "MinValue": 0,
            "Thresholds": [
                {
                    "Direction": "greater than",
                    "Name": "upper critical",
                    "Severity": 1,
                    "Value": 3.45
                },
                {
                    "Direction": "less than",
                    "Name": "lower critical",
                    "Severity": 1,
                    "Value": 3.13
                }
            ],
            "Type": "ADC"
        },
        {
            "Index": 5,
            "Name": "VOL_5V_AUX",
            "ScaleFactor": 0.272291,
            "MaxValue": 7,
            "MinValue": 0,
            "Thresholds": [
                {
                    "Direction": "greater than",
                    "Name": "upper critical",
                    "Severity": 1,
                    "Value": 5.25
                },
                {
                    "Direction": "less than",
                    "Name": "lower critical",
                    "Severity": 1,
                    "Value": 4.75
                }
            ],
            "Type": "ADC"
        },
        {
            "Index": 6,
            "Name": "VOL_PCH_1_8V",
            "ScaleFactor": 1,
            "MaxValue": 7,
            "MinValue": 0,
            "Thresholds": [
                {
                    "Direction": "greater than",
                    "Name": "upper critical",
                    "Severity": 1,
                    "Value": 1.89
                },
                {
                    "Direction": "less than",
                    "Name": "lower critical",
                    "Severity": 1,
                    "Value": 1.71
                }
            ],
            "Type": "ADC"
        },
        {
            "Index": 7,
            "Name": "VOL_BATTERY",
            "ScaleFactor": 0.3333,
            "MaxValue": 5,
            "MinValue": 0,
            "Thresholds": [
                {
                    "Direction": "greater than",
                    "Name": "upper critical",
                    "Severity": 1,
                    "Value": 3.15
                },
                {
                    "Direction": "less than",
                    "Name": "lower critical",
                    "Severity": 1,
                    "Value": 2.85
                }
            ],
            "Type": "ADC"
        },
        {
            "Index": 8,
            "Name": "VOL_CPU0_VCORE",
            "ScaleFactor": 0.741602,
            "MaxValue": 18,
            "MinValue": 0,
            "Thresholds": [
                {
                    "Direction": "greater than",
                    "Name": "upper critical",
                    "Severity": 1,
                    "Value": 1.96
                },
                {
                    "Direction": "less than",
                    "Name": "lower critical",
                    "Severity": 1,
                    "Value": 1.78
                }
            ],
            "Type": "ADC"
        },
        {
            "Index": 9,
            "Name": "VOL_CPU1_VCORE",
            "ScaleFactor": 0.741602,
            "MaxValue": 18,
            "MinValue": 0,
            "Thresholds": [
                {
                    "Direction": "greater than",
                    "Name": "upper critical",
                    "Severity": 1,
                    "Value": 1.96
                },
                {
                    "Direction": "less than",
                    "Name": "lower critical",
                    "Severity": 1,
                    "Value": 1.78
                }
            ],
            "Type": "ADC"
        },
        {
            "Index": 10,
            "Name": "VOL_DIMM_ABC",
            "ScaleFactor": 1,
            "MaxValue": 2,
            "MinValue": 0,
            "Thresholds": [
                {
                    "Direction": "greater than",
                    "Name": "upper critical",
                    "Severity": 1,
                    "Value": 1.28
                },
                {
                    "Direction": "less than",
                    "Name": "lower critical",
                    "Severity": 1,
                    "Value": 1.16
                }
            ],
            "Type": "ADC"
        },
        {
            "Index": 11,
            "Name": "VOL_DIMM_DEF",
            "ScaleFactor": 1,
            "MaxValue": 2,
            "MinValue": 0,
            "Thresholds": [
                {
                    "Direction": "greater than",
                    "Name": "upper critical",
                    "Severity": 1,
                    "Value": 1.28
                },
                {
                    "Direction": "less than",
                    "Name": "lower critical",
                    "Severity": 1,
                    "Value": 1.16
                }
            ],
            "Type": "ADC"
        },
        {
            "Index": 12,
            "Name": "VOL_DIMM_GHJ",
            "ScaleFactor": 1,
            "MaxValue": 2,
            "MinValue": 0,
            "Thresholds": [
                {
                    "Direction": "greater than",
                    "Name": "upper critical",
                    "Severity": 1,
                    "Value": 1.28
                },
                {
                    "Direction": "less than",
                    "Name": "lower critical",
                    "Severity": 1,
                    "Value": 1.16
                }
            ],
            "Type": "ADC"
        },
        {
            "Index": 13,
            "Name": "VOL_DIMM_KLM",
            "ScaleFactor": 1,
            "MaxValue": 2,
            "MinValue": 0,
            "Thresholds": [
                {
                    "Direction": "greater than",
                    "Name": "upper critical",
                    "Severity": 1,
                    "Value": 1.28
                },
                {
                    "Direction": "less than",
                    "Name": "lower critical",
                    "Severity": 1,
                    "Value": 1.16
                }
            ],
            "Type": "ADC"
        },
        {
            "Index": 14,
            "Name": "VOL_SYS0_VCCIO",
            "ScaleFactor": 0.741602,
            "MaxValue": 18,
            "MinValue": 0,
            "Thresholds": [
                {
                    "Direction": "greater than",
                    "Name": "upper critical",
                    "Severity": 1,
                    "Value": 1.96
                },
                {
                    "Direction": "less than",
                    "Name": "lower critical",
                    "Severity": 1,
                    "Value": 1.78
                }
            ],
            "Type": "ADC"
        },
        {
            "Index": 15,
            "Name": "VOL_SYS1_VCCIO",
            "ScaleFactor": 0.741602,
            "MaxValue": 18,
            "MinValue": 0,
            "Thresholds": [
                {
                    "Direction": "greater than",
                    "Name": "upper critical",
                    "Severity": 1,
                    "Value": 1.96
                },
                {
                    "Direction": "less than",
                    "Name": "lower critical",
                    "Severity": 1,
                    "Value": 1.78
                }
            ],
            "Type": "ADC"
        },
        {
            "Address": "0x49",
            "Bus": 6,
            "Name": "TEMP_AMB_0",
            "Thresholds": [
                    {
                        "Direction": "greater than",
                        "Name": "upper critical",
                        "Severity": 1,
                        "Value": 40
                    }
            ],
            "Type": "TMP75"
        },

        {
            "Address": "0x4a",
            "Bus": 6,
            "Name": "TEMP_AMB_1",
            "Thresholds": [
                    {
                        "Direction": "greater than",
                        "Name": "upper critical",
                        "Severity": 1,
                        "Value": 40
                    }
            ],
            "Type": "TMP75"
        }
    ],
    "Name": "hs9216 Main Board",
    "Probe": "xyz.openbmc_project.FruDevice({'BOARD_PRODUCT_NAME' : '.*1621*'})",
    "Type": "Board",
    "xyz.openbmc_project.Inventory.Decorator.Asset": {
        "Manufacturer": "$PRODUCT_MANUFACTURER",
        "Model": "$PRODUCT_PRODUCT_NAME",
        "PartNumber": "$PRODUCT_PART_NUMBER",
        "SerialNumber": "$PRODUCT_SERIAL_NUMBER"
    }    
}
